{
  "apiVersion": "v1",
  "kind": "Namespace",
  "metadata": {
    "creationTimestamp": "2025-07-01T15:54:41Z",
    "deletionTimestamp": "2025-07-01T19:28:18Z",
    "labels": {
      "kubernetes.io/metadata.name": "arc-systems"
    },
    "name": "arc-systems",
    "resourceVersion": "287599",
    "uid": "53079e14-10cc-45ba-8ae9-dd19ceb008b0"
  },
  "spec": {},
  "status": {
    "conditions": [
      {
        "lastTransitionTime": "2025-07-01T19:28:23Z",
        "message": "All resources successfully discovered",
        "reason": "ResourcesDiscovered",
        "status": "False",
        "type": "NamespaceDeletionDiscoveryFailure"
      },
      {
        "lastTransitionTime": "2025-07-01T19:28:23Z",
        "message": "All legacy kube types successfully parsed",
        "reason": "ParsedGroupVersions",
        "status": "False",
        "type": "NamespaceDeletionGroupVersionParsingFailure"
      },
      {
        "lastTransitionTime": "2025-07-01T19:28:23Z",
        "message": "All content successfully deleted, may be waiting on finalization",
        "reason": "ContentDeleted",
        "status": "False",
        "type": "NamespaceDeletionContentFailure"
      },
      {
        "lastTransitionTime": "2025-07-01T19:28:23Z",
        "message": "Some resources are remaining: rolebindings.rbac.authorization.k8s.io has 1 resource instances, roles.rbac.authorization.k8s.io has 1 resource instances, serviceaccounts. has 1 resource instances",
        "reason": "SomeResourcesRemain",
        "status": "True",
        "type": "NamespaceContentRemaining"
      },
      {
        "lastTransitionTime": "2025-07-01T19:28:23Z",
        "message": "Some content in the namespace has finalizers remaining: actions.github.com/cleanup-protection in 3 resource instances",
        "reason": "SomeFinalizersRemain",
        "status": "True",
        "type": "NamespaceFinalizersRemaining"
      }
    ],
    "phase": "Terminating"
  }
}
